SimulatedLIBS/__init__.py
SimulatedLIBS/animation.py
SimulatedLIBS/py.typed
SimulatedLIBS/simulation.py
SimulatedLIBS-1.1.0.dist-info/LICENSE.md
SimulatedLIBS-1.1.0.dist-info/METADATA
SimulatedLIBS-1.1.0.dist-info/WHEEL
SimulatedLIBS-1.1.0.dist-info/top_level.txt
SimulatedLIBS-1.1.0.dist-info/RECORD
