Metadata-Version: 2.1
Name: SimulatedLIBS
Version: 1.1.0
Summary: SimulatedLIBS provides simple Python class to simulate LIBS spectra with NIST LIBS Database interface
Home-page: https://github.com/MKastek/SimulatedLIBS
Author: Marcin Kastek
Author-email: marcin.kastek@ifpilm.pl
License: MIT
Classifier: Programming Language :: Python :: 3
Classifier: Programming Language :: Python :: 3.8
Classifier: Programming Language :: Python :: 3.8
Classifier: Programming Language :: Python :: 3.9
Classifier: Programming Language :: Python :: 3.10
Requires-Python: >=3.8
License-File: LICENSE.md
Requires-Dist: pandas
Requires-Dist: numpy
Requires-Dist: matplotlib
Requires-Dist: requests
Requires-Dist: bs4
Requires-Dist: scipy
Requires-Dist: selenium
Requires-Dist: webdriver-manager
Provides-Extra: testing
Requires-Dist: pytest >=6.0 ; extra == 'testing'
Requires-Dist: pytest-cov >=2.0 ; extra == 'testing'
Requires-Dist: mypy >=0.910 ; extra == 'testing'
Requires-Dist: flake8 >=3.9 ; extra == 'testing'
Requires-Dist: tox >=3.24 ; extra == 'testing'
